Metadata-Version: 1.2
Name: clubhouse-lib
Version: 1.0.0
Summary: The unofficial Python client library for the Clubhouse API.
Home-page: https://github.com/huntrar/python-clubhouse-lib
Author: Hunter H
Author-email: huntrar@gmail.com
Maintainer: Hunter H
Maintainer-email: huntrar@gmail.com
License: MIT
Keywords: clubhouse clubhouse-lib clubhouse-api
Platform: UNKNOWN
Classifier: Development Status :: 5 - Production/Stable
Classifier: Environment :: Web Environment
Classifier: Intended Audience :: Developers
Classifier: License :: OSI Approved :: MIT License
Classifier: Operating System :: OS Independent
Classifier: Programming Language :: Python :: 3
Classifier: Programming Language :: Python :: 3.8
Classifier: Topic :: Software Development :: Bug Tracking
